llmify/__init__.py
llmify/guessing.py
llmify/inference.py
llmify/llmify.py
llmify_decorator-1.0.0.dist-info/METADATA
llmify_decorator-1.0.0.dist-info/WHEEL
llmify_decorator-1.0.0.dist-info/licenses/LICENSE
llmify_decorator-1.0.0.dist-info/RECORD
