Metadata-Version: 2.4
Name: llmify-decorator
Version: 1.0.0
Summary: Library for replacing function calls with LLM inference.
Project-URL: Repository, https://github.com/dross20/llmify
Author-email: Drew Ross <drewross@ku.edu>
License: MIT License
License-File: LICENSE
Keywords: experimental,llm,nlp,openai,prototyping,python
Classifier: Development Status :: 3 - Alpha
Classifier: License :: OSI Approved :: MIT License
Classifier: Operating System :: OS Independent
Classifier: Programming Language :: Python :: 3
Classifier: Topic :: Scientific/Engineering :: Artificial Intelligence
Requires-Python: >=3.9
